vbproblemcomposer/__init__.py
vbproblemcomposer/__main__.py
vbproblemcomposer/choice_option.py
vbproblemcomposer/compose.py
vbproblemcomposer/functions.py
vbproblemcomposer/main.py
vbproblemcomposer-0.1.3.dist-info/METADATA
vbproblemcomposer-0.1.3.dist-info/WHEEL
vbproblemcomposer-0.1.3.dist-info/entry_points.txt
vbproblemcomposer-0.1.3.dist-info/RECORD
